.gitignore
CHANGELOG
LICENSE
MANIFEST
PKGBUILD
README.rst
requirements.txt
setup.py
docs/Makefile
docs/api.rst
docs/conf.py
docs/index.rst
docs/make.bat
docs/requirements.txt
picuplib/__init__.py
picuplib/checks.py
picuplib/exceptions.py
picuplib/globals.py
picuplib/misc.py
picuplib/upload.py
picuplib.egg-info/PKG-INFO
picuplib.egg-info/SOURCES.txt
picuplib.egg-info/dependency_links.txt
picuplib.egg-info/requires.txt
picuplib.egg-info/top_level.txt